aldryn_redirects/__init__.py
aldryn_redirects/admin.py
aldryn_redirects/apps.py
aldryn_redirects/middleware.py
aldryn_redirects/models.py
aldryn_redirects/locale/ar/LC_MESSAGES/django.po
aldryn_redirects/locale/az/LC_MESSAGES/django.po
aldryn_redirects/locale/bg/LC_MESSAGES/django.po
aldryn_redirects/locale/bn/LC_MESSAGES/django.po
aldryn_redirects/locale/bs/LC_MESSAGES/django.po
aldryn_redirects/locale/ca/LC_MESSAGES/django.po
aldryn_redirects/locale/cs/LC_MESSAGES/django.po
aldryn_redirects/locale/cy/LC_MESSAGES/django.po
aldryn_redirects/locale/da/LC_MESSAGES/django.po
aldryn_redirects/locale/de/LC_MESSAGES/django.po
aldryn_redirects/locale/el/LC_MESSAGES/django.po
aldryn_redirects/locale/en/LC_MESSAGES/django.po
aldryn_redirects/locale/en_GB/LC_MESSAGES/django.po
aldryn_redirects/locale/eo/LC_MESSAGES/django.po
aldryn_redirects/locale/es/LC_MESSAGES/django.po
aldryn_redirects/locale/es_AR/LC_MESSAGES/django.po
aldryn_redirects/locale/es_MX/LC_MESSAGES/django.po
aldryn_redirects/locale/et/LC_MESSAGES/django.po
aldryn_redirects/locale/eu/LC_MESSAGES/django.po
aldryn_redirects/locale/fa/LC_MESSAGES/django.po
aldryn_redirects/locale/fi/LC_MESSAGES/django.po
aldryn_redirects/locale/fr/LC_MESSAGES/django.po
aldryn_redirects/locale/fy_NL/LC_MESSAGES/django.po
aldryn_redirects/locale/ga/LC_MESSAGES/django.po
aldryn_redirects/locale/gl/LC_MESSAGES/django.po
aldryn_redirects/locale/he/LC_MESSAGES/django.po
aldryn_redirects/locale/hi/LC_MESSAGES/django.po
aldryn_redirects/locale/hr/LC_MESSAGES/django.po
aldryn_redirects/locale/hu/LC_MESSAGES/django.po
aldryn_redirects/locale/id/LC_MESSAGES/django.po
aldryn_redirects/locale/is/LC_MESSAGES/django.po
aldryn_redirects/locale/it/LC_MESSAGES/django.po
aldryn_redirects/locale/ja/LC_MESSAGES/django.po
aldryn_redirects/locale/ka/LC_MESSAGES/django.po
aldryn_redirects/locale/kk/LC_MESSAGES/django.po
aldryn_redirects/locale/km/LC_MESSAGES/django.po
aldryn_redirects-1.0.0.dist-info/DESCRIPTION.rst
aldryn_redirects-1.0.0.dist-info/METADATA
aldryn_redirects-1.0.0.dist-info/RECORD
aldryn_redirects-1.0.0.dist-info/WHEEL
aldryn_redirects-1.0.0.dist-info/metadata.json
aldryn_redirects-1.0.0.dist-info/top_level.txt
