Metadata-Version: 2.0
Name: aldryn-redirects
Version: 1.0.0
Summary: A modified version of django.contrib.redirects with multilingual target URLs.
Home-page: https://github.com/aldryn/aldryn-redirects
Author: Divio AG
Author-email: info@divio.ch
License: LICENSE.txt
Platform: OS Independent
Classifier: Development Status :: 4 - Beta
Classifier: Environment :: Web Environment
Classifier: Framework :: Django
Classifier: Intended Audience :: Developers
Classifier: License :: OSI Approved :: BSD License
Classifier: Operating System :: OS Independent
Classifier: Programming Language :: Python
Classifier: Topic :: Internet :: WWW/HTTP :: Dynamic Content
Classifier: Topic :: Software Development
Classifier: Topic :: Software Development :: Libraries :: Application Frameworks
Requires-Dist: aldryn-translation-tools
Requires-Dist: django-parler
